{
  "fecha_actualizacion": "2025-12-30T16:06:39.710336",
  "fuente": "INEGI Sakbe API",
  "resumen": {
    "ciudades_con_datos_sakbe": 40,
    "distancia_promedio_km": 489.9,
    "costo_casetas_promedio": 1189.0,
    "costo_combustible_promedio": 2154.0,
    "costo_total_promedio": 3343.0
  },
  "rutas_principales": [
    {
      "ciudad": "Monterrey",
      "clientes_fcarnes": 905,
      "distancia_km": 3.29,
      "costo_casetas_mxn": 0.0,
      "costo_combustible_mxn": 14.46613,
      "costo_total_mxn": 14.46613
    },
    {
      "ciudad": "Victoria",
      "clientes_fcarnes": 520,
      "distancia_km": 282.95,
      "costo_casetas_mxn": 0.0,
      "costo_combustible_mxn": 1244.13115,
      "costo_total_mxn": 1244.13115
    },
    {
      "ciudad": "Guadalupe",
      "clientes_fcarnes": 337,
      "distancia_km": 11.41,
      "costo_casetas_mxn": 0.0,
      "costo_combustible_mxn": 50.16977,
      "costo_total_mxn": 50.16977
    },
    {
      "ciudad": "Reynosa",
      "clientes_fcarnes": 188,
      "distancia_km": 220.54,
      "costo_casetas_mxn": 748.0,
      "costo_combustible_mxn": 969.71438,
      "costo_total_mxn": 1717.71438
    },
    {
      "ciudad": "Apodaca",
      "clientes_fcarnes": 129,
      "distancia_km": 18.57,
      "costo_casetas_mxn": 0.0,
      "costo_combustible_mxn": 81.65229000000001,
      "costo_total_mxn": 81.65229000000001
    },
    {
      "ciudad": "Juárez",
      "clientes_fcarnes": 75,
      "distancia_km": 23.85,
      "costo_casetas_mxn": 0.0,
      "costo_combustible_mxn": 104.86845,
      "costo_total_mxn": 104.86845
    },
    {
      "ciudad": "Saltillo",
      "clientes_fcarnes": 59,
      "distancia_km": 92.87,
      "costo_casetas_mxn": 294.0,
      "costo_combustible_mxn": 408.34939,
      "costo_total_mxn": 702.3493900000001
    },
    {
      "ciudad": "Benito Juárez",
      "clientes_fcarnes": 48,
      "distancia_km": 23.85,
      "costo_casetas_mxn": 0.0,
      "costo_combustible_mxn": 104.86845,
      "costo_total_mxn": 104.86845
    },
    {
      "ciudad": "Benito Juárez",
      "clientes_fcarnes": 48,
      "distancia_km": 23.85,
      "costo_casetas_mxn": 0.0,
      "costo_combustible_mxn": 104.86845,
      "costo_total_mxn": 104.86845
    },
    {
      "ciudad": "Torreón",
      "clientes_fcarnes": 9,
      "distancia_km": 331.17,
      "costo_casetas_mxn": 849.0,
      "costo_combustible_mxn": 1456.15449,
      "costo_total_mxn": 2305.15449
    },
    {
      "ciudad": "Tijuana",
      "clientes_fcarnes": 8,
      "distancia_km": 2228.47,
      "costo_casetas_mxn": 3809.0,
      "costo_combustible_mxn": 9798.58259,
      "costo_total_mxn": 13607.58259
    },
    {
      "ciudad": "San Luis Potosí",
      "clientes_fcarnes": 7,
      "distancia_km": 509.82,
      "costo_casetas_mxn": 745.0,
      "costo_combustible_mxn": 2241.67854,
      "costo_total_mxn": 2986.67854
    },
    {
      "ciudad": "Chihuahua",
      "clientes_fcarnes": 6,
      "distancia_km": 801.14,
      "costo_casetas_mxn": 1952.0,
      "costo_combustible_mxn": 3522.6125800000004,
      "costo_total_mxn": 5474.612580000001
    },
    {
      "ciudad": "Culiacán",
      "clientes_fcarnes": 5,
      "distancia_km": 1035.25,
      "costo_casetas_mxn": 4704.0,
      "costo_combustible_mxn": 4551.99425,
      "costo_total_mxn": 9255.99425
    },
    {
      "ciudad": "Aguascalientes",
      "clientes_fcarnes": 4,
      "distancia_km": 568.56,
      "costo_casetas_mxn": 747.0,
      "costo_combustible_mxn": 2499.95832,
      "costo_total_mxn": 3246.95832
    },
    {
      "ciudad": "Puebla",
      "clientes_fcarnes": 3,
      "distancia_km": 1017.5,
      "costo_casetas_mxn": 2255.0,
      "costo_combustible_mxn": 4473.9475,
      "costo_total_mxn": 6728.9475
    },
    {
      "ciudad": "Querétaro",
      "clientes_fcarnes": 3,
      "distancia_km": 699.78,
      "costo_casetas_mxn": 922.0,
      "costo_combustible_mxn": 3076.93266,
      "costo_total_mxn": 3998.93266
    },
    {
      "ciudad": "Durango",
      "clientes_fcarnes": 3,
      "distancia_km": 583.13,
      "costo_casetas_mxn": 2315.0,
      "costo_combustible_mxn": 2564.02261,
      "costo_total_mxn": 4879.02261
    },
    {
      "ciudad": "Tampico",
      "clientes_fcarnes": 3,
      "distancia_km": 510.86,
      "costo_casetas_mxn": 64.0,
      "costo_combustible_mxn": 2246.25142,
      "costo_total_mxn": 2310.25142
    },
    {
      "ciudad": "León",
      "clientes_fcarnes": 2,
      "distancia_km": 690.19,
      "costo_casetas_mxn": 1321.0,
      "costo_combustible_mxn": 3034.7654300000004,
      "costo_total_mxn": 4355.76543
    }
  ]
}